MANIFEST.in
f5.py
setup.py
pyf5/__init__.py
pyf5/__init__.pyc
pyf5/server.py
pyf5/utils.py
pyf5/zfs.py
pyf5.egg-info/PKG-INFO
pyf5.egg-info/SOURCES.txt
pyf5.egg-info/dependency_links.txt
pyf5.egg-info/requires.txt
pyf5.egg-info/top_level.txt
pyf5/_/index.html
pyf5/_/css/bootstrap-responsive.css
pyf5/_/css/bootstrap-responsive.min.css
pyf5/_/css/bootstrap.css
pyf5/_/css/bootstrap.min.css
pyf5/_/css/index.less
pyf5/_/img/bullet_green.png
pyf5/_/img/glyphicons-halflings-white.png
pyf5/_/img/glyphicons-halflings.png
pyf5/_/img/file-icons/DIR.png
pyf5/_/img/file-icons/css.png
pyf5/_/img/file-icons/flash.png
pyf5/_/img/file-icons/html.png
pyf5/_/img/file-icons/img.png
pyf5/_/img/file-icons/js.png
pyf5/_/img/file-icons/php.png
pyf5/_/img/file-icons/unknown.png
pyf5/_/js/index.js
pyf5/_/js/reloader.js
pyf5/_/js/libs/bootstrap.js
pyf5/_/js/libs/bootstrap.min.js
pyf5/_/js/libs/jquery-1.8.2.min.js
pyf5/_/js/libs/jquery.cookie.js
pyf5/_/js/libs/knockout-2.2.1.js
pyf5/_/js/libs/less.js
pyf5/handlers/__init__.py
pyf5/handlers/api.py
pyf5/handlers/default.py