Metadata-Version: 1.0
Name: pyf5
Version: 0.9.1.1
Summary: Web page auto reloader for web developers.
Home-page: http://getf5.com
Author: luwenjin
Author-email: luwenjin@gmail.com
License: UNKNOWN
Platform: UNKNOWN
